maximum_agents/__init__.py
maximum_agents/abstract.py
maximum_agents/base.py
maximum_agents/basicblogpost.md
maximum_agents/builders/builder.py
maximum_agents/datastore/__init__.py
maximum_agents/datastore/backends.py
maximum_agents/datastore/core.py
maximum_agents/datastore/types.py
maximum_agents/document_types.py
maximum_agents/exponential_backoff.py
maximum_agents/pydantic_final_answer_tools.py
maximum_agents/records.py
maximum_agents/tools.py
maximum_agents-0.1.6.dist-info/METADATA
maximum_agents-0.1.6.dist-info/WHEEL
maximum_agents-0.1.6.dist-info/RECORD
