Metadata-Version: 2.3
Name: maximum-agents
Version: 0.1.6
Summary: A powerful Python framework for building intelligent agents with structured outputs, document generation, database integration, and advanced hook-based customization.
License: MIT
Keywords: ai,agents,llm,pydantic,automation,framework
Author: Lukas Nel
Author-email: lukas@lotushealth.ai
Requires-Python: >=3.12
Classifier: Development Status :: 4 - Beta
Classifier: Intended Audience :: Developers
Classifier: License :: OSI Approved :: MIT License
Classifier: Operating System :: OS Independent
Classifier: Programming Language :: Python :: 3
Classifier: Programming Language :: Python :: 3.12
Classifier: Programming Language :: Python :: 3.13
Classifier: Topic :: Software Development :: Libraries :: Python Modules
Classifier: Topic :: Scientific/Engineering :: Artificial Intelligence
Classifier: Topic :: Software Development :: Libraries :: Application Frameworks
Requires-Dist: Pillow (>=10.0.0,<11.0.0)
Requires-Dist: duckdb (>=0.9.0,<1.0.0)
Requires-Dist: numpy (>=2.3.1,<3.0.0)
Requires-Dist: pandas (>=2.0.0,<3.0.0)
Requires-Dist: pydantic (>=2.11.7,<3.0.0)
Requires-Dist: python-docx (>=1.2.0,<2.0.0)
Requires-Dist: python-pptx (>=1.0.2,<2.0.0)
Requires-Dist: rasterio (>=1.4.3,<2.0.0)
Requires-Dist: smolagents[litellm] (>=1.20.0,<2.0.0)
Project-URL: Bug Tracker, https://github.com/LukasNel/maximum_agents/issues
Project-URL: Documentation, https://maximum-agents.readthedocs.io/
Project-URL: Homepage, https://github.com/LukasNel/maximum_agents
Project-URL: Repository, https://github.com/LukasNel/maximum_agents
